hooker/__init__.py
hooker/__main__.py
hooker/api.py
hooker/event_list.py
hooker/hook_list.py
hooker/logger.py
hooker-1.0.2.dist-info/LICENSE
hooker-1.0.2.dist-info/METADATA
hooker-1.0.2.dist-info/WHEEL
hooker-1.0.2.dist-info/top_level.txt
hooker-1.0.2.dist-info/RECORD
