Metadata-Version: 2.1
Name: hooker
Version: 1.0.2
Summary: An arcane-powered python hooking library for sane humans
Home-page: https://github.com/satori-ng/hooker
Author: Satori-NG org
Author-email: satori_ng@email.com
Keywords: hook,event,plugin,extension,module
License-File: LICENSE
